[{"name":"μ‹ ν• πππ¶ μ¤4π‘ π½πΌν”ν”20","id":"UCRkjM0k--qT6ZkS7ynRAMag","detectedTime":"2023-12-06T11:28:29.173Z"},{"name":"μ‹ ν• πππ¶ μ¤4π‘ π½πΌν”ν”20","id":"UC6fgcjUDVnb3cNXxKSu59nQ","detectedTime":"2023-12-07T00:23:33.528Z"},{"name":"μ‹ ν• πππ¶ μ¤4π‘ π½πΌν”ν”20","id":"UCxDyqtrQKBwtHnwtbfyZN_g","detectedTime":"2023-12-07T13:28:21.484Z"},{"name":"μ‹ ν• πππ¶ μ¤4π‘ π½πΌν”ν”20","id":"UCG55JLMfx8el6FhAwUqlB-g","detectedTime":"2023-12-08T13:34:12.622Z"},{"name":"μ‹ ν• πππ¶ μ¤4π‘ π½πΌν”ν”20","id":"UCm5V6UNxz9R6gQRo-nXYliw","detectedTime":"2023-12-09T17:16:15.460Z"},{"name":"μ‹ ν• πππ¶ μ¤4π‘ π½πΌν”ν”20","id":"UCRsaEs6yvqcxPF5Ln61aVuQ","detectedTime":"2023-12-22T08:00:06.557Z"}]